mesh/__init__.py
mesh/__main__.py
mesh/gretap.py
mesh/mesh.py
mesh/node.py
mesh/pulumi/__init__.py
mesh/pulumi/main.py
mesh/pulumi/resource.py
mesh/pulumi/util.py
mesh/remote.py
mesh/types.py
mesh/util.py
wireguard_mesh-0.2.5.dist-info/METADATA
wireguard_mesh-0.2.5.dist-info/WHEEL
wireguard_mesh-0.2.5.dist-info/entry_points.txt
wireguard_mesh-0.2.5.dist-info/RECORD
