Metadata-Version: 2.1
Name: wireguard-mesh
Version: 0.2.5
Summary: A Wireguard L2 Mesh Network Automation Tool
Home-page: https://github.com/sitbon/wireguard-mesh
License: AGPLv3
Keywords: wireguard,mesh,vpn,networking
Author: Phillip Sitbon
Author-email: phillip.sitbon@gmail.com
Requires-Python: >=3.11,<4.0
Classifier: Development Status :: 4 - Beta
Classifier: Environment :: Console
Classifier: Intended Audience :: System Administrators
Classifier: License :: OSI Approved :: GNU Affero General Public License v3
Classifier: License :: Other/Proprietary License
Classifier: Operating System :: POSIX :: Linux
Classifier: Programming Language :: Python :: 3
Classifier: Programming Language :: Python :: 3.11
Classifier: Programming Language :: Python :: 3.12
Classifier: Topic :: System :: Networking
Classifier: Topic :: System :: Systems Administration
Provides-Extra: pulumi
Requires-Dist: attrs (>=23.1.0,<24.0.0)
Requires-Dist: fabric (>=3.2.2,<4.0.0)
Requires-Dist: pulumi (>=3.96.1,<4.0.0) ; extra == "pulumi"
Requires-Dist: pyyaml (>=6.0.1,<7.0.0)
Requires-Dist: wireguard-tools (>=0.4.4,<0.5.0)
Project-URL: Repository, https://github.com/sitbon/wireguard-mesh
